README
setup.py
passwordly/__init__.py
passwordly/hash.py
passwordly/password.py
passwordly.egg-info/PKG-INFO
passwordly.egg-info/SOURCES.txt
passwordly.egg-info/dependency_links.txt
passwordly.egg-info/requires.txt
passwordly.egg-info/top_level.txt
passwordly.egg-info/zip-safe