Metadata-Version: 1.1
Name: passwordly
Version: 0.5
Summary: Simple library for generating passwordly passwords
Home-page: https://github.com/passwordly/passwordly-python
Author: Josh Yudaken
Author-email: UNKNOWN
License: UNKNOWN
Download-URL: http://pypi.python.org/pypi/passwordly/
Keywords: passwordly
Platform: UNKNOWN
Classifier: Development Status :: 5 - Production/Stable
Classifier: Intended Audience :: Developers
Classifier: License :: OSI Approved :: MIT License
Classifier: Natural Language :: English
Classifier: Operating System :: OS Independent
Classifier: Programming Language :: Python
Classifier: Topic :: Software Development :: Libraries :: Python Modules
